Workbook

Sheet Dashboard
B2: CSM Operating System
B3: Dashboard — Slate & TARDIS Blue Edition
B5: Total ARR | C5: Accounts | D5: Retention Rate | E5: Open Tasks | F5: Avg Health | G5: Wins This Qtr | H5: Upcoming Renewals | I5: Overdue Tasks
B6: =SUM(Accounts!C2:C100) -> 480000 | C6: =COUNTA(Accounts!A2:A100) -> 5 | D6: =TEXT(1-(COUNTIF(Accounts!F2:F100,"Churned")/COUNTA(Accounts!A2:A100)),"0%") -> 100% | E6: =COUNTIF(Tasks!C2:C500,"<>Done") -> 499 | F6: =IF(COUNTA(Accounts!A2:A100)>0,ROUND((COUNTIF(Accounts!E2:E100,"Green 🟢")*3+COUNTIF(Accounts!E2:E100,"Yellow 🟡")*2+COUNTIF(Accounts!E2:E100,"Red 🔴")*1)/COUNTA(Accounts!A2:A100),1),0) -> 2.4 | G6: =COUNTIFS('Brag Book'!C2:C500,">="&DATE(YEAR(TODAY()),IF(MONTH(TODAY())<=3,1,IF(MONTH(TODAY())<=6,4,IF(MONTH(TODAY())<=9,7,10))),1),'Brag Book'!C2:C500,"<="&TODAY()) -> 0 | H6: =COUNTIFS(Accounts!D2:D100,">="&TODAY(),Accounts!D2:D100,"<="&TODAY()+90) -> 2 | I6: =COUNTIFS(Tasks!E2:E500,"<"&TODAY(),Tasks!C2:C500,"<>Done") -> 0
B9: Account Health Breakdown | F9: Upcoming Renewals (Next 90 Days)
B10: Health | C10: Count | D10: ARR | E10: % of Book | F10: Account | G10: ARR | H10: Renewal Date | I10: Health
B11: Green 🟢 | C11: =COUNTIF(Accounts!E2:E100,"Green 🟢") -> 3 | D11: =SUMIF(Accounts!E2:E100,"Green 🟢",Accounts!C2:C100) -> 195000 | E11: =IF(SUM(Accounts!C2:C100)>0,C11/SUM(Accounts!C2:C100),0) -> 6.25e-06 | F11: =IFERROR(INDEX(Accounts!A2:A100,MATCH(SMALL(IF((Accounts!D2:D100>=TODAY())*(Accounts!D2:D100<=TODAY()+90),Accounts!D2:D100),1),Accounts!D2:D100,0)),"") | G11: =IFERROR(INDEX(Accounts!C2:C100,MATCH(SMALL(IF((Accounts!D2:D100>=TODAY())*(Accounts!D2:D100<=TODAY()+90),Accounts!D2:D100),1),Accounts!D2:D100,0)),"") | H11: =IFERROR(INDEX(Accounts!D2:D100,MATCH(SMALL(IF((Accounts!D2:D100>=TODAY())*(Accounts!D2:D100<=TODAY()+90),Accounts!D2:D100),1),Accounts!D2:D100,0)),"") | I11: =IFERROR(INDEX(Accounts!E2:E100,MATCH(SMALL(IF((Accounts!D2:D100>=TODAY())*(Accounts!D2:D100<=TODAY()+90),Accounts!D2:D100),1),Accounts!D2:D100,0)),"")
B12: Yellow 🟡 | C12: =COUNTIF(Accounts!E2:E100,"Yellow 🟡") -> 1 | D12: =SUMIF(Accounts!E2:E100,"Yellow 🟡",Accounts!C2:C100) -> 85000 | E12: =IF(SUM(Accounts!C2:C100)>0,C12/SUM(Accounts!C2:C100),0) -> 2.0833333e-06 | F12: =IFERROR(INDEX(Accounts!A2:A100,MATCH(SMALL(IF((Accounts!D2:D100>=TODAY())*(Accounts!D2:D100<=TODAY()+90),Accounts!D2:D100),2),Accounts!D2:D100,0)),"") | G12: =IFERROR(INDEX(Accounts!C2:C100,MATCH(SMALL(IF((Accounts!D2:D100>=TODAY())*(Accounts!D2:D100<=TODAY()+90),Accounts!D2:D100),2),Accounts!D2:D100,0)),"") | H12: =IFERROR(INDEX(Accounts!D2:D100,MATCH(SMALL(IF((Accounts!D2:D100>=TODAY())*(Accounts!D2:D100<=TODAY()+90),Accounts!D2:D100),2),Accounts!D2:D100,0)),"") | I12: =IFERROR(INDEX(Accounts!E2:E100,MATCH(SMALL(IF((Accounts!D2:D100>=TODAY())*(Accounts!D2:D100<=TODAY()+90),Accounts!D2:D100),2),Accounts!D2:D100,0)),"")
B13: Red 🔴 | C13: =COUNTIF(Accounts!E2:E100,"Red 🔴") -> 1 | D13: =SUMIF(Accounts!E2:E100,"Red 🔴",Accounts!C2:C100) -> 200000 | E13: =IF(SUM(Accounts!C2:C100)>0,C13/SUM(Accounts!C2:C100),0) -> 2.0833333e-06 | F13: =IFERROR(INDEX(Accounts!A2:A100,MATCH(SMALL(IF((Accounts!D2:D100>=TODAY())*(Accounts!D2:D100<=TODAY()+90),Accounts!D2:D100),3),Accounts!D2:D100,0)),"") | G13: =IFERROR(INDEX(Accounts!C2:C100,MATCH(SMALL(IF((Accounts!D2:D100>=TODAY())*(Accounts!D2:D100<=TODAY()+90),Accounts!D2:D100),3),Accounts!D2:D100,0)),"") | H13: =IFERROR(INDEX(Accounts!D2:D100,MATCH(SMALL(IF((Accounts!D2:D100>=TODAY())*(Accounts!D2:D100<=TODAY()+90),Accounts!D2:D100),3),Accounts!D2:D100,0)),"") | I13: =IFERROR(INDEX(Accounts!E2:E100,MATCH(SMALL(IF((Accounts!D2:D100>=TODAY())*(Accounts!D2:D100<=TODAY()+90),Accounts!D2:D100),3),Accounts!D2:D100,0)),"")
F14: =IFERROR(INDEX(Accounts!A2:A100,MATCH(SMALL(IF((Accounts!D2:D100>=TODAY())*(Accounts!D2:D100<=TODAY()+90),Accounts!D2:D100),4),Accounts!D2:D100,0)),"") | G14: =IFERROR(INDEX(Accounts!C2:C100,MATCH(SMALL(IF((Accounts!D2:D100>=TODAY())*(Accounts!D2:D100<=TODAY()+90),Accounts!D2:D100),4),Accounts!D2:D100,0)),"") | H14: =IFERROR(INDEX(Accounts!D2:D100,MATCH(SMALL(IF((Accounts!D2:D100>=TODAY())*(Accounts!D2:D100<=TODAY()+90),Accounts!D2:D100),4),Accounts!D2:D100,0)),"") | I14: =IFERROR(INDEX(Accounts!E2:E100,MATCH(SMALL(IF((Accounts!D2:D100>=TODAY())*(Accounts!D2:D100<=TODAY()+90),Accounts!D2:D100),4),Accounts!D2:D100,0)),"")
F15: =IFERROR(INDEX(Accounts!A2:A100,MATCH(SMALL(IF((Accounts!D2:D100>=TODAY())*(Accounts!D2:D100<=TODAY()+90),Accounts!D2:D100),5),Accounts!D2:D100,0)),"") | G15: =IFERROR(INDEX(Accounts!C2:C100,MATCH(SMALL(IF((Accounts!D2:D100>=TODAY())*(Accounts!D2:D100<=TODAY()+90),Accounts!D2:D100),5),Accounts!D2:D100,0)),"") | H15: =IFERROR(INDEX(Accounts!D2:D100,MATCH(SMALL(IF((Accounts!D2:D100>=TODAY())*(Accounts!D2:D100<=TODAY()+90),Accounts!D2:D100),5),Accounts!D2:D100,0)),"") | I15: =IFERROR(INDEX(Accounts!E2:E100,MATCH(SMALL(IF((Accounts!D2:D100>=TODAY())*(Accounts!D2:D100<=TODAY()+90),Accounts!D2:D100),5),Accounts!D2:D100,0)),"")
B16: Priority Tasks — Due This Week & Overdue
B17: Task | C17: Account | D17: Status | E17: Priority | F17: Due Date | G17: Owner | H17: Source | I17: Notes
B18: ← Data populates from the Tasks sheet. Sort by Due Date and filter for this week.
B20: Recent Wins (Last 30 Days)
B21: Win | C21: Account | D21: Date | E21: Category | F21: Revenue Impact | G21: Description
B22: ← Data populates from the Brag Book sheet. Filter for last 30 days.

Sheet Accounts
A1: Account Name | B1: Tier | C1: ARR | D1: Renewal Date | E1: Health Score | F1: Stage | G1: CSM Owner | H1: Main Contact | I1: Secondary Contacts | J1: Industry | K1: Contract Start | L1: Contract Length | M1: Product/Plan | N1: Seats | O1: NPS Score | P1: Last QBR Date | Q1: Next QBR Date | R1: Days to Renewal | S1: CRM Link | T1: Notes
A2: Acme Corp | B2: Enterprise | C2: 120000 | D2: 46280 | E2: Green 🟢 | F2: Expanding | H2: Jane Smith - VP Ops | I2: Tom Lee - Dir Eng | J2: Technology | K2: 45550 | L2: Annual | M2: Enterprise | N2: 150 | O2: 9 | P2: 46032 | Q2: 46122 | R2: =IF(D2="","",D2-TODAY()) -> 166 | T2: Strong champion in Jane
A3: Globex Industries | B3: Mid-Market | C3: 85000 | D3: 46204 | E3: Yellow 🟡 | F3: Adopting | H3: Mike Chen - Head of IT | I3: Sarah Park - PM | J3: Manufacturing | K3: 45839 | L3: Annual | M3: Professional | N3: 75 | O3: 7 | P3: 46006 | Q3: 46096 | R3: =IF(D3="","",D3-TODAY()) -> 90 | T3: Usage dipped Feb — investigate
A4: Initech Solutions | B4: Mid-Market | C4: 45000 | D4: 46356 | E4: Green 🟢 | F4: Renewing | H4: David Kim - COO | J4: Financial Services | K4: 45991 | L4: Annual | M4: Professional | N4: 40 | O4: 8 | P4: 46073 | Q4: 46162 | R4: =IF(D4="","",D4-TODAY()) -> 242 | T4: Smooth account
A5: Wonka Enterprises | B5: Enterprise | C5: 200000 | D5: 46174 | E5: Red 🔴 | F5: At-Risk | H5: Lisa Nguyen - CTO | I5: James Wright - VP Prod | J5: Consumer Goods | K5: 45444 | L5: 2-Year | M5: Enterprise | N5: 300 | O5: 5 | P5: 46047 | Q5: 46113 | R5: =IF(D5="","",D5-TODAY()) -> 60 | T5: Exec sponsor left. Recovery plan active.
A6: Stark Digital | B6: SMB | C6: 30000 | D6: 46402 | E6: Green 🟢 | F6: Onboarding | H6: Peter Grant - Founder | J6: Technology | K6: 46037 | L6: Annual | M6: Starter | N6: 15 | R6: =IF(D6="","",D6-TODAY()) -> 288 | T6: New customer. Week 3 onboarding.

Sheet Tasks
A1: Task | B1: Account | C1: Status | D1: Priority | E1: Due Date | F1: Owner | G1: Source | H1: Category | I1: Notes | J1: Completed Date
A2: Send QBR recap email to Jane | B2: Acme Corp | C2: Not Started | D2: 🟡 High | E2: 46115 | G2: Call | H2: Follow-up | I2: Include usage stats and expansion proposal
A3: Schedule exec sponsor intro call | B3: Wonka Enterprises | C3: In Progress | D3: 🔴 Urgent | E3: 46116 | G3: Internal | H3: Follow-up | I3: New CTO needs relationship building ASAP
A4: Review usage analytics | B4: Globex Industries | C4: Not Started | D4: 🟡 High | E4: 46119 | G4: Internal | H4: Research | I4: Pull last 60 days of login data
A5: Prepare renewal proposal | B5: Initech Solutions | C5: Not Started | D5: 🔵 Medium | E5: 46127 | G5: Internal | H5: Deliverable | I5: Check multi-year discount options
A6: Complete Week 4 training | B6: Stark Digital | C6: Not Started | D6: 🟡 High | E6: 46120 | G6: Call | H6: Deliverable | I6: Peter wants advanced reporting walkthrough
A7: Follow up on ticket #4521 | B7: Globex Industries | C7: Waiting | D7: 🔴 Urgent | E7: 46115 | G7: Support | H7: Customer Request | I7: Integration bug — Mike pinged twice
A8: Share product roadmap preview | B8: Acme Corp | C8: Not Started | D8: ⚪ Low | E8: 46132 | G8: QBR | H8: Follow-up | I8: Jane asked about API improvements
A9: Draft escalation doc | B9: Wonka Enterprises | C9: In Progress | D9: 🔴 Urgent | E9: 46115 | G9: Internal | H9: Deliverable | I9: Need VP sign-off on recovery plan
A10: Send NPS survey | B10: Initech Solutions | C10: Not Started | D10: 🔵 Medium | E10: 46122 | G10: Internal | H10: Follow-up | I10: 90 days since last survey
A11: Connect Peter with community | B11: Stark Digital | C11: Not Started | D11: ⚪ Low | E11: 46123 | G11: Ad-hoc | H11: Follow-up | I11: Wants to meet other users in his industry

Sheet Calls & Meetings
A1: Meeting Title | B1: Account | C1: Date | D1: Type | E1: Attendees | F1: Agenda | G1: Discussion Notes | H1: Key Takeaways | I1: Sentiment | J1: Follow-up Date | K1: Follow-up Done | L1: Recording Link
A2: Acme Corp - QBR - Q1 | B2: Acme Corp | C2: 46032 | D2: QBR | E2: Jane Smith, Tom Lee; Me, Sarah Collins | F2: Q1 review, usage, roadmap, expansion | G2: Usage up 12%. Jane happy with reporting. Tom asked about API. London expansion on track. | H2: Strong champion. API roadmap matters to Tom. | I2: 😊 Positive | J2: 46046 | K2: Yes
A3: Globex - Check-in | B3: Globex Industries | C3: 46096 | D3: Check-in | E3: Mike Chen; Me | F3: Usage dip, ticket status | G3: Restructuring caused usage drop. 3 people moved depts. Need new onboarding. Ticket #4521 still open. | H3: People change, not product issue. Push on ticket. | I3: 😟 Concerned | J3: 46103 | K3: No
A4: Wonka - Escalation | B4: Wonka Enterprises | C4: 46109 | D4: Escalation | E4: Lisa Nguyen, James Wright; Me, Rachel Torres | F4: CTO concerns, recovery plan | G4: Lisa wants hard ROI in 30 days or evaluating alternatives. James sympathetic but not decision maker. | H4: 30-day window. Build relationship with Lisa. | I4: 😠 Negative | J4: 46113 | K4: No
A5: Stark Digital - Onboarding Wk2 | B5: Stark Digital | C5: 46051 | D5: Onboarding | E5: Peter Grant; Me | F5: Core training, setup review | G5: Peter very hands-on, already 80% configured. Breezed through training. Wants advanced reporting. | H5: Power user. Accelerate onboarding. | I5: 😊 Positive | J5: 46058 | K5: Yes
A6: Initech - Renewal Check-in | B6: Initech Solutions | C6: 46073 | D6: Check-in | E6: David Kim; Me | F6: Renewal, satisfaction, reference | G6: Happy. Standard renewal agreed. Volunteered as reference. Compliance team expansion possible. | H6: Easy renewal. David is an advocate. | I6: 😊 Positive | J6: 46101 | K6: Yes

Sheet Brag Book
A1: Win Title | B1: Account | C1: Date | D1: Category | E1: Revenue Impact | F1: Description | G1: Problem | H1: Action Taken | I1: Result | J1: Metrics | K1: Who Was Involved | L1: Review Ready | M1: Quarter | N1: Theme
A2: Saved at-risk renewal via exec realignment | B2: Acme Corp | C2: 46044 | D2: Retention | E2: 120000 | F2: Built business case showing 34% efficiency gain, presented to CFO. Secured 2-year renewal with 10% uplift. | G2: Budget review flagged contract for cuts | H2: Built ROI case, presented to CFO directly, negotiated 2-year term | I2: Renewal secured at $132K/yr | J2: ARR retained: $120K. New: $132K (10% up) | K2: AE: Sarah Collins, SE: Dev Patel | L2: Yes | M2: Q1-2026 | N2: Revenue Retention
A3: Drove adoption 40% → 78% | B3: Globex Industries | C3: 45976 | D3: Adoption | F3: Identified training gap for manufacturing floor. Created quick-start guide, ran 3 sessions. | G3: Low adoption from untrained floor team | H3: Custom guide + 3 targeted training sessions | I3: DAU 30→59, adoption 40%→78% | J3: Support tickets dropped 45% | K3: Support team | L3: Yes | M3: Q4-2025 | N3: Customer Outcomes
A4: Landed London office expansion | B4: Acme Corp | C4: 45899 | D4: Expansion | E4: 48000 | F4: Arranged pilot for London team using competitor. Migration support led to 40-seat expansion. | G4: London team using competitor product | H4: Pilot program, migration support, custom proposal | I4: $48K ARR added, 40 seats | J4: Displaced competitor in London office | K4: AE: Sarah Collins, Tom Lee | L4: Yes | M4: Q3-2025 | N4: Revenue Growth
A5: Built QBR template for CS team | B5: Internal | C5: 46063 | D5: Process | F5: Noticed inconsistent QBR quality. Built standardized template adopted by all 8 CSMs. | G5: QBR quality inconsistent across team | H5: Built template with prep checklist and follow-up framework | I5: All 8 CSMs adopted | J5: Quality scores: 3.2 → 4.1 | K5: CS Manager: Rachel Torres | L5: Yes | M5: Q1-2026 | N5: Process & Leadership
A6: Customer reference closed $500K deal | B6: Initech Solutions | C6: 46086 | D6: Advocacy | F6: David volunteered as reference. His call with prospect COO directly influenced deal close. | G6: Enterprise prospect needed peer validation | H6: Facilitated reference call between David and prospect COO | I6: $500K deal closed | J6: David: 'best vendor relationship we have' | K6: Sales VP: Mark Jensen, AE: Chris Hoang | L6: Yes | M6: Q1-2026 | N6: Strategic Impact

Sheet Projects
A1: Project Name | B1: Account | C1: Status | D1: Type | E1: Priority | F1: Start Date | G1: Target End Date | H1: Owner | I1: Objectives | J1: Milestones | K1: Current Status Update | L1: Risks & Blockers | M1: Outcome | N1: Lessons Learned
A2: Wonka Recovery Plan | B2: Wonka Enterprises | C2: Active | D2: Internal Initiative | E2: High | F2: 46109 | G2: 46140 | I2: Prove ROI to new CTO within 30 days | J2: Wk1: Data pull. Wk2: Business case. Wk3: Exec meeting. Wk4: Decision. | K2: Business case in progress | L2: CTO may decide before plan completes
A3: Stark Digital Onboarding | B3: Stark Digital | C3: Active | D3: Onboarding | E3: High | F3: 46037 | G3: 46127 | I3: Full adoption within 90 days | J3: Day 30: Core features live. Day 60: Advanced features. Day 90: Value review. | K3: Week 3 — ahead of schedule | L3: None currently
A4: QBR Template Standardization | B4: Internal | C4: Completed | D4: Playbook | E4: Medium | F4: 46037 | G4: 46063 | I4: Create consistent QBR experience across CS team | J4: Draft template. Pilot with 2 CSMs. Iterate. Roll out. | K4: Completed — adopted by all 8 CSMs | M4: Quality scores improved 3.2→4.1 | N4: Get buy-in from 2 CSMs first before full rollout

Sheet Goals & OKRs
A1: Goal | B1: Type | C1: Quarter | D1: Key Result 1 | E1: KR1 Target | F1: KR1 Actual | G1: KR1 Progress | H1: Key Result 2 | I1: KR2 Target | J1: KR2 Actual | K1: KR2 Progress | L1: Key Result 3 | M1: KR3 Target | N1: KR3 Actual | O1: KR3 Progress | P1: Status | Q1: Notes
A2: Retain 95% of book ARR | B2: Personal | C2: Q2-2026 | D2: Gross retention rate | E2: 95 | F2: 92 | G2: =IF(E2=0,0,F2/E2) -> 0.96842105 | H2: Zero unforced churn | I2: 0 | J2: 0 | K2: =IF(I2=0,0,J2/I2) -> 0 | L2: Save Wonka renewal | M2: 1 | N2: 0 | O2: =IF(M2=0,0,N2/M2) -> 0 | P2: At Risk | Q2: Wonka is the wildcard
A3: Drive $100K in expansion revenue | B3: Personal | C3: Q2-2026 | D3: Expansion ARR closed | E3: 100000 | F3: 48000 | G3: =IF(E3=0,0,F3/E3) -> 0.48 | H3: Identify 3 expansion opps | I3: 3 | J3: 2 | K3: =IF(I3=0,0,J3/I3) -> 0.66666667 | L3: QBR-sourced expansions | M3: 2 | N3: 1 | O3: =IF(M3=0,0,N3/M3) -> 0.5 | P3: On Track | Q3: Acme London already closed
A4: Improve team QBR quality | B4: Team | C4: Q1-2026 | D4: QBR quality score avg | E4: 4 | F4: 4.1 | G4: =IF(E4=0,0,F4/E4) -> 1.025 | H4: Template adoption | I4: 8 | J4: 8 | K4: =IF(I4=0,0,J4/I4) -> 1 | L4: Peer feedback score | M4: 4 | N4: 3.8 | O4: =IF(M4=0,0,N4/M4) -> 0.95 | P4: Achieved | Q4: Template rollout successful

Sheet Feedback Log
A1: Feedback | B1: Date | C1: Source | D1: Source Name | E1: Type | F1: Category | G1: Action Taken | H1: Resolved
A2: Great job navigating the Wonka escalation — keep leadership posted more frequently | B2: 46111 | C2: Manager | D2: Rachel Torres | E2: Constructive | F2: Communication | G2: Set up daily Slack updates during escalations | H2: Yes
A3: Your QBR template is the best thing to happen to this team | B3: 46068 | C3: Peer | D3: Alex Mendez | E3: Positive | F3: Process
A4: Would love more proactive updates between check-ins | B4: 46073 | C4: Customer | D4: David Kim (Initech) | E4: Constructive | F4: Communication | G4: Added monthly async email updates for all accounts | H4: Yes
A5: Strong cross-functional collaboration on the Acme expansion | B5: 46052 | C5: Manager | D5: Rachel Torres | E5: Positive | F5: Cross-functional

Sheet Weekly Review
B2: Weekly Review
B3: Week of:
B5: ✅ What I accomplished this week
B6: 1.
B7: 2.
B8: 3.
B9: 4.
B10: 5.
B12: 🏆 Wins worth logging
B13: Win | C13: Account | D13: Impact | E13: Add to Brag Book?
B18: 📊 Account health changes
B19: Account | C19: Old Status | D19: New Status | E19: Reason
B24: 🎯 Top 3 priorities for next week
B25: 1.
B26: 2.
B27: 3.
B29: 💭 Notes to self

Sheet How To Use
B2: CSM Operating System — Quick Start Guide
B4: GETTING STARTED
B5: 1. Start with the Accounts tab. Replace the sample data with your real accounts.
B6: 2. Move to Tasks. Add your current action items. Use the dropdowns for Status and Priority.
B7: 3. The Dashboard will auto-populate as you add data to other sheets.
B8: 4. Log every customer call in the Calls & Meetings tab — even quick ones.
B9: 5. Start your Brag Book immediately. Don't wait for review season.
B11: DAILY HABITS (5 min)
B12: • Check your Tasks tab filtered by Due Date = Today
B13: • Log any calls/meetings after they happen
B14: • Add action items from calls immediately
B16: WEEKLY HABITS (15 min)
... B45: • Blue accents = TARDIS blue theme elements (navigation, headers, KPI highlights)
